joinvoice/__init__.py
joinvoice/__main__.py
joinvoice/joinvoice.py
joinvoice-1.0.1.dist-info/LICENSE.txt
joinvoice-1.0.1.dist-info/METADATA
joinvoice-1.0.1.dist-info/WHEEL
joinvoice-1.0.1.dist-info/entry_points.txt
joinvoice-1.0.1.dist-info/top_level.txt
joinvoice-1.0.1.dist-info/RECORD
